setup.py
better_utils/__init__.py
better_utils/args_util.py
better_utils/cmd_util.py
better_utils/collection_util.py
better_utils/file_util.py
better_utils/time_util.py
better_utils.egg-info/PKG-INFO
better_utils.egg-info/SOURCES.txt
better_utils.egg-info/dependency_links.txt
better_utils.egg-info/requires.txt
better_utils.egg-info/top_level.txt