Metadata-Version: 1.0
Name: better-utils
Version: 0.3.6
Summary: A better util project
Home-page: UNKNOWN
Author: UNKNOWN
Author-email: UNKNOWN
License: UNKNOWN
Platform: UNKNOWN
